apix/__init__.py
apix/app.py
apix/attribute.py
apix/authenticator.py
apix/collection.py
apix/comparison.py
apix/comparison_type.py
apix/context.py
apix/cursor.py
apix/cursor_type.py
apix/database.py
apix/direction.py
apix/direction_type.py
apix/document.py
apix/enumeration.py
apix/error.py
apix/error_handler.py
apix/filter.py
apix/filter_type.py
apix/gql.py
apix/model.py
apix/operation.py
apix/operation_type.py
apix/operator.py
apix/order.py
apix/order_type.py
apix/resolver.py
apix/scalar.py
apix/scalar_type.py
apix/select.py
apix/select_type.py
apix/session.py
apix/token.py
apix/update.py
apix/update_type.py
apix/utils.py
apix_core-0.0.10.dist-info/LICENSE.txt
apix_core-0.0.10.dist-info/METADATA
apix_core-0.0.10.dist-info/WHEEL
apix_core-0.0.10.dist-info/RECORD
