Metadata-Version: 2.1
Name: apix-core
Version: 0.0.10
Summary: apiX - The Python framework to create MongoDB-backed applications with GraphQL API web interface.
Home-page: https://apix.org
License: MIT
Keywords: graphql,mongodb,api,starlette,async
Author: Danijel Kivaranovic
Author-email: dan@apix.org
Requires-Python: >=3.11,<4.0
Classifier: License :: OSI Approved :: MIT License
Classifier: Programming Language :: Python :: 3
Classifier: Programming Language :: Python :: 3.11
Provides-Extra: uvicorn
Requires-Dist: graphql-core (>=3.2.3,<4.0.0)
Requires-Dist: motor (>=3.1.1,<4.0.0)
Requires-Dist: pymongo (>=4.3.3,<5.0.0)
Requires-Dist: starlette (>=0.26.1,<0.27.0)
Requires-Dist: uvicorn (>=0.23.2,<0.24.0) ; extra == "uvicorn"
Project-URL: Documentation, https://apix.org
Project-URL: Repository, https://github.com/ApixOrg/apix
